[
  {
    "id": "MTG-1781776089895-518",
    "title": "Q1 Test",
    "date": "2026-06-18",
    "attendees": "",
    "department": "",
    "rawNotes": "",
    "summary": "",
    "status": "",
    "created": "2026-06-18T09:48:09.896Z",
    "updated": "2026-06-18T14:34:53.092Z",
    "raw_notes": "### Q1 2026 Meeting \n1. How the new School Operate and Do Marketing\n   - Add this point in Q2 2026 Meeting\n2. CamAesean + 2 More Major Players, Check how they Promote\n3. Adopt (only if itdoes not degrade the image of school)\n   - Techniques\n   - Programs\n4. Do something like AUPP: Offer Courses\n   1. Double Degree\n   2. Apply to University Fair\n5. SOP on Demotion\n6. Next meeting, Present Problem/Solution\n7. Camtech (Owned by OCIC)\n8. Market Strategy-Discuss More\n9. Boost on Media\n10. Dinner with Chairman (Excom/SM, Gen Committee)\n11. ",
    "taskCount": 0,
    "doneCount": 0
  }
]
